latexdocs/__init__.py
latexdocs/base.py
latexdocs/document.py
latexdocs/items.py
latexdocs/preamble.py
latexdocs/table.py
latexdocs/utils.py
latexdocs-0.0.2.dist-info/LICENSE
latexdocs-0.0.2.dist-info/METADATA
latexdocs-0.0.2.dist-info/WHEEL
latexdocs-0.0.2.dist-info/top_level.txt
latexdocs-0.0.2.dist-info/RECORD
