Metadata-Version: 2.1
Name: latexdocs
Version: 0.0.2
Summary: A Python library to generate publication-ready documents with LaTeX.
Home-page: https://github.com/BALOGHBence/latexdocs
Author: Bence Balogh
Author-email: benceeok@gmail.com
License: UNKNOWN
Download-URL: https://github.com/BALOGHBence/latexdocs/archive/refs/tags/v0.0.2.zip
Platform: UNKNOWN
Classifier: Development Status :: 5 - Production/Stable
Classifier: License :: OSI Approved :: MIT License
Classifier: Programming Language :: Python :: 3.7
Classifier: Programming Language :: Python :: 3.8
Classifier: Programming Language :: Python :: 3.9
Classifier: Programming Language :: Python :: 3.10
Classifier: Programming Language :: Python :: 3 :: Only
Classifier: Operating System :: OS Independent
Requires-Python: >=3.7, <3.11
Requires-Dist: setuptools
Requires-Dist: wheel
Requires-Dist: six
Requires-Dist: linkeddeepdict
Requires-Dist: pylatex
